xot/__init__.py
xot/language_models/__init__.py
xot/language_models/anthropic.py
xot/language_models/base_language_model.py
xot/language_models/gemini.py
xot/language_models/openai.py
xot/main.py
xot/strategies/__init__.py
xot/strategies/base_strategy.py
xot/strategies/cot.py
xot/strategies/pot.py
xot/strategies/tir.py
xot/tools/__init__.py
xot/tools/base_tool.py
xot/tools/calculator.py
xot/tools/linux_term.py
xot/tools/sql_db.py
xot/tools/symbolic_solver.py
xot/tools/web_search.py
xot-0.1.2.dist-info/LICENSE
xot-0.1.2.dist-info/METADATA
xot-0.1.2.dist-info/WHEEL
xot-0.1.2.dist-info/RECORD
