Metadata-Version: 2.1
Name: xot
Version: 0.1.2
Summary: a package with modular components for building X of Though (XoT) systems
Author: Jackmin801
Author-email: ongjackm@gmail.com
Requires-Python: >=3.11,<4.0
Classifier: Programming Language :: Python :: 3
Classifier: Programming Language :: Python :: 3.11
Classifier: Programming Language :: Python :: 3.12
Requires-Dist: datasets (>=2.21.0,<3.0.0)
